{"song":{"player1":"bf-car","songId":"high","songName":"High","splitVoiceTracks":true,"style":"Default","notes":[{"sectionNotes":[],"lengthInSteps":16,"endTime":1920,"bpm":125,"mustHitSection":true,"startTime":0},{"sectionNotes":[],"lengthInSteps":16,"endTime":3840,"bpm":125,"mustHitSection":true,"startTime":1920},{"playerSec":false,"sectionNotes":[[3840,0,0,"Normal"],[4320,0,0,"Normal"],[4560,3,0,"Normal"],[4800,0,0,"Normal"],[5160,3,0,"Normal"],[5520,0,0,"Normal"]],"lengthInSteps":16,"endTime":5760,"bpm":125,"mustHitSection":false,"startTime":3840},{"playerSec":false,"sectionNotes":[[5760,0,0,"Normal"],[6240,0,0,"Normal"],[6480,3,0,"Normal"],[6720,0,0,"Normal"],[7080,3,0,"Normal"],[7440,0,0,"Normal"]],"lengthInSteps":16,"endTime":7680,"bpm":125,"mustHitSection":false,"startTime":5760},{"playerSec":false,"sectionNotes":[[7680,0,0,"Normal"],[8160,0,0,"Normal"],[8400,3,0,"Normal"],[8640,3,0,"Normal"],[9000,0,0,"Normal"],[9360,3,0,"Normal"]],"lengthInSteps":16,"endTime":9600,"bpm":125,"mustHitSection":false,"startTime":7680},{"playerSec":false,"sectionNotes":[[9600,2,0,"Normal"],[9840,2,0,"Normal"],[10080,0,0,"Normal"],[10320,0,0,"Normal"],[10560,3,0,"Normal"],[10800,2,0,"Normal"],[11040,2,0,"Normal"],[11280,0,0,"Normal"]],"lengthInSteps":16,"endTime":11520,"bpm":125,"mustHitSection":false,"startTime":9600},{"playerSec":true,"sectionNotes":[[11520,4,0,"Normal"],[12000,4,0,"Normal"],[12240,7,0,"Normal"],[12480,4,0,"Normal"],[12840,7,0,"Normal"],[13200,4,0,"Normal"]],"lengthInSteps":16,"endTime":13440,"bpm":125,"mustHitSection":true,"startTime":11520},{"playerSec":true,"sectionNotes":[[13440,4,0,"Normal"],[13920,4,0,"Normal"],[14160,7,0,"Normal"],[14400,4,0,"Normal"],[14760,7,0,"Normal"],[15120,4,0,"Normal"]],"lengthInSteps":16,"endTime":15360,"bpm":125,"mustHitSection":true,"startTime":13440},{"playerSec":true,"sectionNotes":[[15360,4,0,"Normal"],[15840,4,0,"Normal"],[16080,7,0,"Normal"],[16320,7,0,"Normal"],[16680,4,0,"Normal"],[17040,7,0,"Normal"]],"lengthInSteps":16,"endTime":17280,"bpm":125,"mustHitSection":true,"startTime":15360},{"playerSec":true,"sectionNotes":[[17280,6,0,"Normal"],[17280,2,360,"Normal"],[17520,6,0,"Normal"],[17760,3,360,"Normal"],[17760,4,0,"Normal"],[18000,4,0,"Normal"],[18240,0,360,"Normal"],[18240,7,0,"Normal"],[18480,6,0,"Normal"],[18720,1,360,"Normal"],[18720,6,0,"Normal"],[18960,4,0,"Normal"]],"lengthInSteps":16,"endTime":19200,"bpm":125,"mustHitSection":true,"startTime":17280},{"playerSec":false,"sectionNotes":[[19200,2,0,"Normal"],[19440,1,0,"Normal"],[19680,3,0,"Normal"],[20040,1,0,"Normal"],[20160,3,0,"Normal"],[20520,3,0,"Normal"],[20880,3,0,"Normal"]],"lengthInSteps":16,"endTime":21120,"bpm":125,"mustHitSection":false,"startTime":19200},{"playerSec":false,"sectionNotes":[[21120,2,0,"Normal"],[21360,1,0,"Normal"],[21600,3,0,"Normal"],[21960,1,0,"Normal"],[22080,0,0,"Normal"],[22440,3,0,"Normal"],[22800,2,0,"Normal"],[22920,0,0,"Normal"]],"lengthInSteps":16,"endTime":23040,"bpm":125,"mustHitSection":false,"startTime":21120},{"playerSec":false,"sectionNotes":[[23280,0,0,"Normal"],[23520,3,0,"Normal"],[24000,2,0,"Normal"],[24360,2,0,"Normal"],[24720,2,0,"Normal"]],"lengthInSteps":16,"endTime":24960,"bpm":125,"mustHitSection":false,"startTime":23040},{"playerSec":false,"sectionNotes":[[24960,2,0,"Normal"],[24960,6,360,"Normal"],[25200,0,0,"Normal"],[25440,2,0,"Normal"],[25440,7,360,"Normal"],[25680,0,0,"Normal"],[25920,3,0,"Normal"],[25920,4,360,"Normal"],[26160,1,0,"Normal"],[26400,3,0,"Normal"],[26400,5,360,"Normal"],[26640,1,0,"Normal"]],"lengthInSteps":16,"endTime":26880,"bpm":125,"mustHitSection":false,"startTime":24960},{"playerSec":true,"sectionNotes":[[26880,6,0,"Normal"],[27120,5,0,"Normal"],[27360,7,0,"Normal"],[27720,5,0,"Normal"],[27840,7,0,"Normal"],[28200,7,0,"Normal"],[28560,7,0,"Normal"]],"lengthInSteps":16,"endTime":28800,"bpm":125,"mustHitSection":true,"startTime":26880},{"playerSec":true,"sectionNotes":[[28800,6,0,"Normal"],[29040,5,0,"Normal"],[29280,7,0,"Normal"],[29640,5,0,"Normal"],[29760,4,0,"Normal"],[30120,7,0,"Normal"],[30480,6,0,"Normal"],[30600,4,0,"Normal"]],"lengthInSteps":16,"endTime":30720,"bpm":125,"mustHitSection":true,"startTime":28800},{"playerSec":true,"sectionNotes":[[30960,4,0,"Normal"],[31200,7,0,"Normal"],[31680,6,0,"Normal"],[32040,6,0,"Normal"],[32400,6,0,"Normal"]],"lengthInSteps":16,"endTime":32640,"bpm":125,"mustHitSection":true,"startTime":30720},{"playerSec":true,"sectionNotes":[[32640,6,0,"Normal"],[32880,4,0,"Normal"],[33120,6,0,"Normal"],[33360,4,0,"Normal"],[33600,7,0,"Normal"],[33840,5,0,"Normal"],[34080,7,0,"Normal"],[34320,5,0,"Normal"]],"lengthInSteps":16,"endTime":34560,"bpm":125,"mustHitSection":true,"startTime":32640},{"playerSec":false,"sectionNotes":[[34560,0,0,"Normal"],[34800,2,0,"Normal"],[35040,1,360,"Normal"],[35520,0,360,"Normal"],[36000,3,360,"Normal"]],"lengthInSteps":16,"endTime":36480,"bpm":125,"mustHitSection":false,"startTime":34560},{"playerSec":false,"sectionNotes":[[36480,3,0,"Normal"],[36840,1,0,"Normal"],[36960,3,0,"Normal"],[37200,0,0,"Normal"],[37440,3,240,"Normal"],[37800,1,0,"Normal"],[37920,0,240,"Normal"],[38280,1,0,"Normal"]],"lengthInSteps":16,"endTime":38400,"bpm":125,"mustHitSection":false,"startTime":36480},{"playerSec":false,"sectionNotes":[[38400,2,360,"Normal"],[38880,3,360,"Normal"],[39360,0,360,"Normal"],[39840,2,360,"Normal"]],"lengthInSteps":16,"endTime":40320,"bpm":125,"mustHitSection":false,"startTime":38400},{"playerSec":false,"sectionNotes":[[40320,3,0,"Normal"],[40560,2,0,"Normal"],[40800,0,0,"Normal"],[41040,2,0,"Normal"],[41280,0,240,"Normal"],[41640,3,0,"Normal"],[41760,1,240,"Normal"],[42120,2,0,"Normal"]],"lengthInSteps":16,"endTime":42240,"bpm":125,"mustHitSection":false,"startTime":40320},{"playerSec":true,"sectionNotes":[[42240,3,360,"Normal"],[42240,4,0,"Normal"],[42480,6,0,"Normal"],[42720,1,360,"Normal"],[42720,5,360,"Normal"],[43200,4,360,"Normal"],[43200,3,360,"Normal"],[43680,0,360,"Normal"],[43680,7,360,"Normal"]],"lengthInSteps":16,"endTime":44160,"bpm":125,"mustHitSection":true,"startTime":42240},{"playerSec":true,"sectionNotes":[[44160,2,360,"Normal"],[44160,7,0,"Normal"],[44520,5,0,"Normal"],[44640,7,0,"Normal"],[44880,4,0,"Normal"],[45120,0,240,"Normal"],[45120,7,240,"Normal"],[45480,1,0,"Normal"],[45480,5,0,"Normal"],[45600,3,240,"Normal"],[45600,4,240,"Normal"],[45960,1,0,"Normal"],[45960,5,0,"Normal"]],"lengthInSteps":16,"endTime":46080,"bpm":125,"mustHitSection":true,"startTime":44160},{"playerSec":true,"sectionNotes":[[46080,2,360,"Normal"],[46080,6,360,"Normal"],[46560,3,1440,"Normal"],[46560,7,360,"Normal"],[47040,4,360,"Normal"],[47520,6,360,"Normal"]],"lengthInSteps":16,"endTime":48000,"bpm":125,"mustHitSection":true,"startTime":46080},{"playerSec":true,"sectionNotes":[[48000,7,0,"Normal"],[48240,6,0,"Normal"],[48480,4,0,"Normal"],[48720,6,0,"Normal"],[48960,4,240,"Normal"],[49320,7,0,"Normal"],[49440,5,240,"Normal"],[49800,6,0,"Normal"]],"lengthInSteps":16,"endTime":49920,"bpm":125,"mustHitSection":true,"startTime":48000},{"playerSec":false,"sectionNotes":[[49920,1,600,"Normal"],[49920,5,720,"Normal"],[50640,3,0,"Normal"],[50880,3,0,"Normal"],[51240,2,0,"Normal"],[51360,0,240,"Normal"]],"lengthInSteps":16,"endTime":51840,"bpm":125,"mustHitSection":false,"startTime":49920},{"playerSec":false,"sectionNotes":[[51840,2,360,"Normal"],[52320,1,0,"Normal"],[52560,3,0,"Normal"],[52800,3,0,"Normal"],[53160,2,0,"Normal"],[53280,0,240,"Normal"]],"lengthInSteps":16,"endTime":53760,"bpm":125,"mustHitSection":false,"startTime":51840},{"playerSec":false,"sectionNotes":[[53760,1,360,"Normal"],[54240,0,0,"Normal"],[54480,3,0,"Normal"],[54720,3,0,"Normal"],[55080,2,0,"Normal"],[55200,0,240,"Normal"]],"lengthInSteps":16,"endTime":55680,"bpm":125,"mustHitSection":false,"startTime":53760},{"playerSec":false,"sectionNotes":[[55680,0,0,"Normal"],[55920,0,0,"Normal"],[56160,3,0,"Normal"],[56280,2,0,"Normal"],[56400,3,0,"Normal"],[56640,0,0,"Normal"],[56760,1,0,"Normal"],[56880,0,0,"Normal"],[57120,1,0,"Normal"],[57360,3,0,"Normal"]],"lengthInSteps":16,"endTime":57600,"bpm":125,"mustHitSection":false,"startTime":55680},{"playerSec":true,"sectionNotes":[[57600,1,480,"Normal"],[57600,5,600,"Normal"],[58320,7,0,"Normal"],[58560,7,0,"Normal"],[58920,6,0,"Normal"],[59040,4,240,"Normal"]],"lengthInSteps":16,"endTime":59520,"bpm":125,"mustHitSection":true,"startTime":57600},{"playerSec":true,"sectionNotes":[[59520,6,360,"Normal"],[60000,5,0,"Normal"],[60240,7,0,"Normal"],[60480,7,0,"Normal"],[60840,6,0,"Normal"],[60960,4,240,"Normal"]],"lengthInSteps":16,"endTime":61440,"bpm":125,"mustHitSection":true,"startTime":59520},{"playerSec":true,"sectionNotes":[[61440,5,360,"Normal"],[61920,4,0,"Normal"],[62160,7,0,"Normal"],[62400,7,0,"Normal"],[62760,6,0,"Normal"],[62880,4,240,"Normal"]],"lengthInSteps":16,"endTime":63360,"bpm":125,"mustHitSection":true,"startTime":61440},{"playerSec":true,"sectionNotes":[[63360,4,0,"Normal"],[63600,4,0,"Normal"],[63840,7,0,"Normal"],[63960,6,0,"Normal"],[64080,7,0,"Normal"],[64320,4,0,"Normal"],[64440,5,0,"Normal"],[64560,4,0,"Normal"],[64800,5,0,"Normal"],[65040,7,0,"Normal"]],"lengthInSteps":16,"endTime":65280,"bpm":125,"mustHitSection":true,"startTime":63360},{"playerSec":false,"sectionNotes":[[65280,0,0,"Normal"],[65280,5,480,"Normal"],[65520,2,0,"Normal"],[65760,1,360,"Normal"],[66240,0,360,"Normal"],[66720,3,360,"Normal"]],"lengthInSteps":16,"endTime":67200,"bpm":125,"mustHitSection":false,"startTime":65280},{"playerSec":false,"sectionNotes":[[67200,3,0,"Normal"],[67560,1,0,"Normal"],[67680,3,0,"Normal"],[67920,0,0,"Normal"],[68160,3,240,"Normal"],[68520,1,0,"Normal"],[68640,0,240,"Normal"],[69000,1,0,"Normal"]],"lengthInSteps":16,"endTime":69120,"bpm":125,"mustHitSection":false,"startTime":67200},{"playerSec":false,"sectionNotes":[[69120,2,360,"Normal"],[69600,3,360,"Normal"],[70080,0,360,"Normal"],[70560,2,360,"Normal"]],"lengthInSteps":16,"endTime":71040,"bpm":125,"mustHitSection":false,"startTime":69120},{"playerSec":false,"sectionNotes":[[71040,3,0,"Normal"],[71280,2,0,"Normal"],[71520,0,0,"Normal"],[71760,2,0,"Normal"],[72000,0,240,"Normal"],[72360,3,0,"Normal"],[72480,1,240,"Normal"],[72840,2,0,"Normal"]],"lengthInSteps":16,"endTime":72960,"bpm":125,"mustHitSection":false,"startTime":71040},{"playerSec":true,"sectionNotes":[[72960,3,360,"Normal"],[72960,4,0,"Normal"],[73200,6,0,"Normal"],[73440,1,360,"Normal"],[73440,5,360,"Normal"],[73920,4,360,"Normal"],[73920,3,360,"Normal"],[74400,0,360,"Normal"],[74400,7,360,"Normal"]],"lengthInSteps":16,"endTime":74880,"bpm":125,"mustHitSection":true,"startTime":72960},{"playerSec":true,"sectionNotes":[[74880,2,360,"Normal"],[74880,7,0,"Normal"],[75240,5,0,"Normal"],[75360,7,0,"Normal"],[75600,4,0,"Normal"],[75840,0,240,"Normal"],[75840,7,240,"Normal"],[76200,1,0,"Normal"],[76200,5,0,"Normal"],[76320,3,240,"Normal"],[76320,4,240,"Normal"],[76680,1,0,"Normal"],[76680,5,0,"Normal"]],"lengthInSteps":16,"endTime":76800,"bpm":125,"mustHitSection":true,"startTime":74880},{"playerSec":true,"sectionNotes":[[76800,2,360,"Normal"],[76800,6,360,"Normal"],[77280,3,1440,"Normal"],[77280,7,360,"Normal"],[77760,4,360,"Normal"],[78240,6,360,"Normal"]],"lengthInSteps":16,"endTime":78720,"bpm":125,"mustHitSection":true,"startTime":76800},{"playerSec":true,"sectionNotes":[[78720,7,0,"Normal"],[78960,6,0,"Normal"],[79200,4,0,"Normal"],[79440,6,0,"Normal"],[79680,4,240,"Normal"],[80040,7,0,"Normal"],[80160,5,240,"Normal"],[80520,6,0,"Normal"]],"lengthInSteps":16,"endTime":80640,"bpm":125,"mustHitSection":true,"startTime":78720},{"playerSec":true,"sectionNotes":[[80640,7,960,"Normal"],[80640,3,960,"Normal"],[82080,6,360,"Normal"],[82080,2,360,"Normal"]],"lengthInSteps":16,"endTime":82560,"bpm":125,"mustHitSection":true,"startTime":80640},{"playerSec":true,"sectionNotes":[[82560,1,600,"Normal"],[82560,5,360,"Normal"],[83040,5,0,"Normal"],[83280,2,600,"Normal"],[83280,6,360,"Normal"],[83760,6,0,"Normal"],[84000,7,360,"Normal"],[84000,3,360,"Normal"]],"lengthInSteps":16,"endTime":84480,"bpm":125,"mustHitSection":true,"startTime":82560},{"playerSec":true,"sectionNotes":[[84480,2,0,"Normal"],[84480,6,360,"Normal"],[84720,3,0,"Normal"],[84960,5,360,"Normal"],[85080,1,0,"Normal"],[85200,3,0,"Normal"],[85320,0,0,"Normal"],[85440,7,360,"Normal"],[85680,3,0,"Normal"],[85800,0,0,"Normal"],[85920,3,0,"Normal"],[85920,4,360,"Normal"],[86040,1,0,"Normal"]],"lengthInSteps":16,"endTime":86400,"bpm":125,"mustHitSection":true,"startTime":84480},{"playerSec":true,"sectionNotes":[[86400,2,0,"Normal"],[86400,6,360,"Normal"],[86640,3,0,"Normal"],[86880,5,360,"Normal"],[87000,1,0,"Normal"],[87120,3,0,"Normal"],[87240,0,0,"Normal"],[87360,7,360,"Normal"],[87600,3,0,"Normal"],[87720,0,0,"Normal"],[87840,3,0,"Normal"],[87840,4,0,"Normal"],[87960,1,0,"Normal"],[88080,7,0,"Normal"]],"lengthInSteps":16,"endTime":88320,"bpm":125,"mustHitSection":true,"startTime":86400},{"playerSec":true,"sectionNotes":[[88320,7,960,"Normal"],[88320,3,960,"Normal"],[89760,6,360,"Normal"],[89760,2,360,"Normal"]],"lengthInSteps":16,"endTime":90240,"bpm":125,"mustHitSection":true,"startTime":88320},{"playerSec":false,"sectionNotes":[[90240,5,600,"Normal"],[90240,1,360,"Normal"],[90720,1,0,"Normal"],[90960,6,600,"Normal"],[90960,2,360,"Normal"],[91440,2,0,"Normal"],[91680,7,0,"Normal"],[91680,3,360,"Normal"],[91920,4,0,"Normal"]],"lengthInSteps":16,"endTime":92160,"bpm":125,"mustHitSection":false,"startTime":90240},{"playerSec":true,"sectionNotes":[[92160,6,0,"Normal"],[92160,2,360,"Normal"],[92400,7,0,"Normal"],[92640,4,0,"Normal"],[92640,1,360,"Normal"],[92880,7,0,"Normal"],[93120,5,0,"Normal"],[93120,3,360,"Normal"],[93360,7,0,"Normal"],[93600,4,0,"Normal"],[93600,0,360,"Normal"],[93840,7,0,"Normal"]],"lengthInSteps":16,"endTime":94080,"bpm":125,"mustHitSection":true,"startTime":92160},{"playerSec":true,"sectionNotes":[[94080,6,0,"Normal"],[94080,2,360,"Normal"],[94320,7,0,"Normal"],[94560,7,0,"Normal"],[94560,1,360,"Normal"],[94680,5,0,"Normal"],[94800,7,0,"Normal"],[94920,4,0,"Normal"],[95040,6,0,"Normal"],[95040,3,360,"Normal"],[95280,7,0,"Normal"],[95520,7,0,"Normal"],[95520,0,0,"Normal"],[95640,5,0,"Normal"],[95640,2,0,"Normal"],[95760,7,0,"Normal"],[95760,3,0,"Normal"],[95880,4,0,"Normal"]],"lengthInSteps":16,"endTime":96000,"bpm":125,"mustHitSection":true,"startTime":94080},{"playerSec":true,"sectionNotes":[[96000,2,960,"Normal"],[96000,6,960,"Normal"]],"lengthInSteps":16,"endTime":97920,"bpm":125,"mustHitSection":true,"startTime":96000},{"sectionNotes":[],"lengthInSteps":16,"endTime":99840,"bpm":125,"mustHitSection":true,"startTime":97920},{"sectionNotes":[],"lengthInSteps":16,"endTime":101760,"bpm":125,"mustHitSection":true,"startTime":99840},{"sectionNotes":[],"lengthInSteps":16,"endTime":103680,"bpm":125,"mustHitSection":true,"startTime":101760},{"sectionNotes":[],"lengthInSteps":16,"endTime":105600,"bpm":125,"mustHitSection":true,"startTime":103680},{"endTime":107520,"altAnim":false,"mustHitSection":true,"lengthInSteps":16,"typeOfSection":0,"sectionNotes":[],"changeBPM":false,"startTime":105600,"bpm":125},{"endTime":109440,"playerAltAnim":false,"altAnim":false,"CPUAltAnim":false,"mustHitSection":true,"lengthInSteps":16,"typeOfSection":0,"sectionNotes":[],"bpm":125,"startTime":107520,"changeBPM":false},{"endTime":111360,"playerAltAnim":false,"altAnim":false,"CPUAltAnim":false,"mustHitSection":true,"lengthInSteps":16,"typeOfSection":0,"sectionNotes":[],"bpm":125,"startTime":109440,"changeBPM":false},{"endTime":113280,"playerAltAnim":false,"altAnim":false,"CPUAltAnim":false,"mustHitSection":true,"lengthInSteps":16,"typeOfSection":0,"sectionNotes":[],"bpm":125,"startTime":111360,"changeBPM":false},{"endTime":115200,"playerAltAnim":false,"altAnim":false,"CPUAltAnim":false,"mustHitSection":true,"lengthInSteps":16,"typeOfSection":0,"sectionNotes":[],"bpm":125,"startTime":113280,"changeBPM":false},{"endTime":117120,"playerAltAnim":false,"altAnim":false,"CPUAltAnim":false,"mustHitSection":true,"lengthInSteps":16,"typeOfSection":0,"sectionNotes":[],"bpm":125,"startTime":115200,"changeBPM":false},{"endTime":119040,"playerAltAnim":false,"altAnim":false,"CPUAltAnim":false,"mustHitSection":true,"lengthInSteps":16,"typeOfSection":0,"sectionNotes":[],"bpm":125,"startTime":117120,"changeBPM":false},{"endTime":120960,"playerAltAnim":false,"altAnim":false,"CPUAltAnim":false,"mustHitSection":true,"lengthInSteps":16,"typeOfSection":0,"sectionNotes":[],"bpm":125,"startTime":119040,"changeBPM":false},{"endTime":122880,"playerAltAnim":false,"altAnim":false,"CPUAltAnim":false,"mustHitSection":true,"lengthInSteps":16,"typeOfSection":0,"sectionNotes":[],"bpm":125,"startTime":120960,"changeBPM":false},{"endTime":124800,"playerAltAnim":false,"altAnim":false,"CPUAltAnim":false,"mustHitSection":true,"lengthInSteps":16,"typeOfSection":0,"sectionNotes":[],"bpm":125,"startTime":122880,"changeBPM":false},{"endTime":126720,"playerAltAnim":false,"altAnim":false,"CPUAltAnim":false,"mustHitSection":true,"lengthInSteps":16,"typeOfSection":0,"sectionNotes":[],"bpm":125,"startTime":124800,"changeBPM":false},{"endTime":128640,"playerAltAnim":false,"altAnim":false,"CPUAltAnim":false,"mustHitSection":true,"lengthInSteps":16,"typeOfSection":0,"sectionNotes":[],"bpm":125,"startTime":126720,"changeBPM":false},{"endTime":130560,"playerAltAnim":false,"altAnim":false,"CPUAltAnim":false,"mustHitSection":true,"lengthInSteps":16,"typeOfSection":0,"sectionNotes":[],"bpm":125,"startTime":128640,"changeBPM":false},{"endTime":132480,"playerAltAnim":false,"altAnim":false,"CPUAltAnim":false,"mustHitSection":true,"lengthInSteps":16,"typeOfSection":0,"sectionNotes":[],"bpm":125,"startTime":130560,"changeBPM":false},{"endTime":134400,"playerAltAnim":false,"altAnim":false,"CPUAltAnim":false,"mustHitSection":true,"lengthInSteps":16,"typeOfSection":0,"sectionNotes":[],"bpm":125,"startTime":132480,"changeBPM":false},{"endTime":136320,"playerAltAnim":false,"altAnim":false,"CPUAltAnim":false,"mustHitSection":true,"lengthInSteps":16,"typeOfSection":0,"sectionNotes":[],"bpm":125,"startTime":134400,"changeBPM":false},{"endTime":138240,"playerAltAnim":false,"altAnim":false,"CPUAltAnim":false,"mustHitSection":true,"lengthInSteps":16,"typeOfSection":0,"sectionNotes":[],"bpm":125,"startTime":136320,"changeBPM":false},{"endTime":140160,"playerAltAnim":false,"altAnim":false,"CPUAltAnim":false,"mustHitSection":true,"lengthInSteps":16,"typeOfSection":0,"sectionNotes":[],"bpm":125,"startTime":138240,"changeBPM":false},{"endTime":142080,"playerAltAnim":false,"altAnim":false,"CPUAltAnim":false,"mustHitSection":true,"lengthInSteps":16,"typeOfSection":0,"sectionNotes":[],"bpm":125,"startTime":140160,"changeBPM":false},{"endTime":144000,"playerAltAnim":false,"altAnim":false,"CPUAltAnim":false,"mustHitSection":true,"lengthInSteps":16,"typeOfSection":0,"sectionNotes":[],"bpm":125,"startTime":142080,"changeBPM":false},{"endTime":145920,"playerAltAnim":false,"altAnim":false,"CPUAltAnim":false,"mustHitSection":true,"lengthInSteps":16,"typeOfSection":0,"sectionNotes":[],"bpm":125,"startTime":144000,"changeBPM":false},{"endTime":147840,"playerAltAnim":false,"altAnim":false,"CPUAltAnim":false,"mustHitSection":true,"lengthInSteps":16,"typeOfSection":0,"sectionNotes":[],"bpm":125,"startTime":145920,"changeBPM":false},{"endTime":149760,"playerAltAnim":false,"altAnim":false,"CPUAltAnim":false,"mustHitSection":true,"lengthInSteps":16,"typeOfSection":0,"sectionNotes":[],"bpm":125,"startTime":147840,"changeBPM":false},{"endTime":151680,"playerAltAnim":false,"altAnim":false,"CPUAltAnim":false,"mustHitSection":true,"lengthInSteps":16,"typeOfSection":0,"sectionNotes":[],"bpm":125,"startTime":149760,"changeBPM":false},{"endTime":153600,"playerAltAnim":false,"altAnim":false,"CPUAltAnim":false,"mustHitSection":true,"lengthInSteps":16,"typeOfSection":0,"sectionNotes":[],"bpm":125,"startTime":151680,"changeBPM":false},{"endTime":155520,"playerAltAnim":false,"altAnim":false,"CPUAltAnim":false,"mustHitSection":true,"lengthInSteps":16,"typeOfSection":0,"sectionNotes":[],"bpm":125,"startTime":153600,"changeBPM":false},{"endTime":157440,"playerAltAnim":false,"altAnim":false,"CPUAltAnim":false,"mustHitSection":true,"lengthInSteps":16,"typeOfSection":0,"sectionNotes":[],"bpm":125,"startTime":155520,"changeBPM":false},{"endTime":159360,"playerAltAnim":false,"altAnim":false,"CPUAltAnim":false,"mustHitSection":true,"lengthInSteps":16,"typeOfSection":0,"sectionNotes":[],"bpm":125,"startTime":157440,"changeBPM":false},{"endTime":161280,"playerAltAnim":false,"altAnim":false,"CPUAltAnim":false,"mustHitSection":true,"lengthInSteps":16,"typeOfSection":0,"sectionNotes":[],"bpm":125,"startTime":159360,"changeBPM":false},{"endTime":163200,"playerAltAnim":false,"altAnim":false,"CPUAltAnim":false,"mustHitSection":true,"lengthInSteps":16,"typeOfSection":0,"sectionNotes":[],"bpm":125,"startTime":161280,"changeBPM":false},{"endTime":165120,"playerAltAnim":false,"altAnim":false,"CPUAltAnim":false,"mustHitSection":true,"lengthInSteps":16,"typeOfSection":0,"sectionNotes":[],"bpm":125,"startTime":163200,"changeBPM":false},{"endTime":167040,"playerAltAnim":false,"altAnim":false,"CPUAltAnim":false,"mustHitSection":true,"lengthInSteps":16,"typeOfSection":0,"sectionNotes":[],"bpm":125,"startTime":165120,"changeBPM":false},{"endTime":168960,"playerAltAnim":false,"altAnim":false,"CPUAltAnim":false,"mustHitSection":true,"lengthInSteps":16,"typeOfSection":0,"sectionNotes":[],"bpm":125,"startTime":167040,"changeBPM":false},{"endTime":170880,"playerAltAnim":false,"altAnim":false,"CPUAltAnim":false,"mustHitSection":true,"lengthInSteps":16,"typeOfSection":0,"sectionNotes":[],"bpm":125,"startTime":168960,"changeBPM":false},{"endTime":172800,"playerAltAnim":false,"altAnim":false,"CPUAltAnim":false,"mustHitSection":true,"lengthInSteps":16,"typeOfSection":0,"sectionNotes":[],"bpm":125,"startTime":170880,"changeBPM":false},{"endTime":174720,"playerAltAnim":false,"altAnim":false,"CPUAltAnim":false,"mustHitSection":true,"lengthInSteps":16,"typeOfSection":0,"sectionNotes":[],"bpm":125,"startTime":172800,"changeBPM":false},{"endTime":176640,"playerAltAnim":false,"altAnim":false,"CPUAltAnim":false,"mustHitSection":true,"lengthInSteps":16,"typeOfSection":0,"sectionNotes":[],"bpm":125,"startTime":174720,"changeBPM":false},{"endTime":178560,"playerAltAnim":false,"altAnim":false,"CPUAltAnim":false,"mustHitSection":true,"lengthInSteps":16,"typeOfSection":0,"sectionNotes":[],"bpm":125,"startTime":176640,"changeBPM":false},{"endTime":180480,"playerAltAnim":false,"altAnim":false,"CPUAltAnim":false,"mustHitSection":true,"lengthInSteps":16,"typeOfSection":0,"sectionNotes":[],"bpm":125,"startTime":178560,"changeBPM":false},{"endTime":182400,"playerAltAnim":false,"altAnim":false,"CPUAltAnim":false,"mustHitSection":true,"lengthInSteps":16,"typeOfSection":0,"sectionNotes":[],"bpm":125,"startTime":180480,"changeBPM":false},{"endTime":184320,"playerAltAnim":false,"altAnim":false,"CPUAltAnim":false,"mustHitSection":true,"lengthInSteps":16,"typeOfSection":0,"sectionNotes":[],"bpm":125,"startTime":182400,"changeBPM":false},{"endTime":186240,"playerAltAnim":false,"altAnim":false,"CPUAltAnim":false,"mustHitSection":true,"lengthInSteps":16,"typeOfSection":0,"sectionNotes":[],"bpm":125,"startTime":184320,"changeBPM":false},{"endTime":188160,"playerAltAnim":false,"altAnim":false,"CPUAltAnim":false,"mustHitSection":true,"lengthInSteps":16,"typeOfSection":0,"sectionNotes":[],"bpm":125,"startTime":186240,"changeBPM":false},{"endTime":190080,"playerAltAnim":false,"altAnim":false,"CPUAltAnim":false,"mustHitSection":true,"lengthInSteps":16,"typeOfSection":0,"sectionNotes":[],"bpm":125,"startTime":188160,"changeBPM":false},{"endTime":192000,"playerAltAnim":false,"altAnim":false,"CPUAltAnim":false,"mustHitSection":true,"lengthInSteps":16,"typeOfSection":0,"sectionNotes":[],"bpm":125,"startTime":190080,"changeBPM":false},{"endTime":193920,"playerAltAnim":false,"altAnim":false,"CPUAltAnim":false,"mustHitSection":true,"lengthInSteps":16,"typeOfSection":0,"sectionNotes":[],"bpm":125,"startTime":192000,"changeBPM":false},{"endTime":195840,"playerAltAnim":false,"altAnim":false,"CPUAltAnim":false,"mustHitSection":true,"lengthInSteps":16,"typeOfSection":0,"sectionNotes":[],"bpm":125,"startTime":193920,"changeBPM":false},{"endTime":197760,"playerAltAnim":false,"altAnim":false,"CPUAltAnim":false,"mustHitSection":true,"lengthInSteps":16,"typeOfSection":0,"sectionNotes":[],"bpm":125,"startTime":195840,"changeBPM":false},{"endTime":199680,"playerAltAnim":false,"altAnim":false,"CPUAltAnim":false,"mustHitSection":true,"lengthInSteps":16,"typeOfSection":0,"sectionNotes":[],"bpm":125,"startTime":197760,"changeBPM":false},{"endTime":201600,"playerAltAnim":false,"altAnim":false,"CPUAltAnim":false,"mustHitSection":true,"lengthInSteps":16,"typeOfSection":0,"sectionNotes":[],"bpm":125,"startTime":199680,"changeBPM":false},{"endTime":203520,"playerAltAnim":false,"altAnim":false,"CPUAltAnim":false,"mustHitSection":true,"lengthInSteps":16,"typeOfSection":0,"sectionNotes":[],"bpm":125,"startTime":201600,"changeBPM":false},{"endTime":205440,"playerAltAnim":false,"altAnim":false,"CPUAltAnim":false,"mustHitSection":true,"lengthInSteps":16,"typeOfSection":0,"sectionNotes":[],"bpm":125,"startTime":203520,"changeBPM":false},{"endTime":207360,"playerAltAnim":false,"altAnim":false,"CPUAltAnim":false,"mustHitSection":true,"lengthInSteps":16,"typeOfSection":0,"sectionNotes":[],"bpm":125,"startTime":205440,"changeBPM":false},{"endTime":209280,"playerAltAnim":false,"altAnim":false,"CPUAltAnim":false,"mustHitSection":true,"lengthInSteps":16,"typeOfSection":0,"sectionNotes":[],"bpm":125,"startTime":207360,"changeBPM":false},{"endTime":211200,"playerAltAnim":false,"altAnim":false,"CPUAltAnim":false,"mustHitSection":true,"lengthInSteps":16,"typeOfSection":0,"sectionNotes":[],"bpm":125,"startTime":209280,"changeBPM":false},{"lengthInSteps":16,"sectionNotes":[],"bpm":125,"playerSec":true,"startTime":211200,"changeBPM":false,"endTime":213120},{"lengthInSteps":16,"sectionNotes":[],"bpm":125,"playerSec":true,"startTime":213120,"changeBPM":false,"endTime":215040},{"lengthInSteps":16,"sectionNotes":[],"bpm":125,"playerSec":true,"startTime":215040,"changeBPM":false,"endTime":216960},{"lengthInSteps":16,"sectionNotes":[],"bpm":125,"playerSec":true,"startTime":216960,"changeBPM":false,"endTime":218880},{"lengthInSteps":16,"sectionNotes":[],"bpm":125,"playerSec":true,"startTime":218880,"changeBPM":false,"endTime":220800},{"lengthInSteps":16,"sectionNotes":[],"bpm":125,"playerSec":true,"startTime":220800,"changeBPM":false,"endTime":222720},{"lengthInSteps":16,"sectionNotes":[],"bpm":125,"playerSec":true,"startTime":222720,"changeBPM":false,"endTime":224640},{"lengthInSteps":16,"sectionNotes":[],"bpm":125,"playerSec":true,"startTime":224640,"changeBPM":false,"endTime":226560},{"lengthInSteps":16,"sectionNotes":[],"bpm":125,"playerSec":true,"startTime":226560,"changeBPM":false,"endTime":228480},{"lengthInSteps":16,"sectionNotes":[],"bpm":125,"playerSec":true,"startTime":228480,"changeBPM":false,"endTime":230400},{"lengthInSteps":16,"sectionNotes":[],"bpm":125,"playerSec":true,"startTime":230400,"changeBPM":false,"endTime":232320},{"lengthInSteps":16,"sectionNotes":[],"bpm":125,"playerSec":true,"startTime":232320,"changeBPM":false,"endTime":234240},{"lengthInSteps":16,"sectionNotes":[],"bpm":125,"playerSec":true,"startTime":234240,"changeBPM":false,"endTime":236160},{"lengthInSteps":16,"sectionNotes":[],"bpm":125,"playerSec":true,"startTime":236160,"changeBPM":false,"endTime":238080},{"lengthInSteps":16,"sectionNotes":[],"bpm":125,"playerSec":true,"startTime":238080,"changeBPM":false,"endTime":240000},{"lengthInSteps":16,"sectionNotes":[],"bpm":125,"playerSec":true,"startTime":240000,"changeBPM":false,"endTime":241920},{"lengthInSteps":16,"sectionNotes":[],"bpm":125,"playerSec":true,"startTime":241920,"changeBPM":false,"endTime":243840},{"lengthInSteps":16,"sectionNotes":[],"bpm":125,"playerSec":true,"startTime":243840,"changeBPM":false,"endTime":245760},{"lengthInSteps":16,"sectionNotes":[],"bpm":125,"playerSec":true,"startTime":245760,"changeBPM":false,"endTime":247680},{"lengthInSteps":16,"sectionNotes":[],"bpm":125,"playerSec":true,"startTime":247680,"changeBPM":false,"endTime":249600},{"lengthInSteps":16,"sectionNotes":[],"bpm":125,"playerSec":true,"startTime":249600,"changeBPM":false,"endTime":251520},{"lengthInSteps":16,"sectionNotes":[],"bpm":125,"playerSec":true,"startTime":251520,"changeBPM":false,"endTime":253440},{"lengthInSteps":16,"sectionNotes":[],"bpm":125,"playerSec":true,"startTime":253440,"changeBPM":false,"endTime":255360},{"lengthInSteps":16,"sectionNotes":[],"bpm":125,"playerSec":true,"startTime":255360,"changeBPM":false,"endTime":257280},{"lengthInSteps":16,"sectionNotes":[],"bpm":125,"playerSec":true,"startTime":257280,"changeBPM":false,"endTime":259200},{"lengthInSteps":16,"sectionNotes":[],"bpm":125,"playerSec":true,"startTime":259200,"changeBPM":false,"endTime":261120},{"lengthInSteps":16,"sectionNotes":[],"bpm":125,"playerSec":true,"startTime":261120,"changeBPM":false,"endTime":263040},{"lengthInSteps":16,"sectionNotes":[],"bpm":125,"playerSec":true,"startTime":263040,"changeBPM":false,"endTime":264960},{"lengthInSteps":16,"sectionNotes":[],"bpm":125,"playerSec":true,"startTime":264960,"changeBPM":false,"endTime":266880},{"lengthInSteps":16,"sectionNotes":[],"bpm":125,"playerSec":true,"startTime":266880,"changeBPM":false,"endTime":268800},{"lengthInSteps":16,"sectionNotes":[],"bpm":125,"playerSec":true,"startTime":268800,"changeBPM":false,"endTime":270720},{"lengthInSteps":16,"sectionNotes":[],"bpm":125,"playerSec":true,"startTime":270720,"changeBPM":false,"endTime":272640},{"lengthInSteps":16,"sectionNotes":[],"bpm":125,"playerSec":true,"startTime":272640,"changeBPM":false,"endTime":274560},{"lengthInSteps":16,"sectionNotes":[],"bpm":125,"playerSec":true,"startTime":274560,"changeBPM":false,"endTime":276480},{"lengthInSteps":16,"sectionNotes":[],"bpm":125,"playerSec":true,"startTime":276480,"changeBPM":false,"endTime":278400},{"lengthInSteps":16,"sectionNotes":[],"bpm":125,"playerSec":true,"startTime":278400,"changeBPM":false,"endTime":280320},{"lengthInSteps":16,"sectionNotes":[],"bpm":125,"playerSec":true,"startTime":280320,"changeBPM":false,"endTime":282240},{"lengthInSteps":16,"sectionNotes":[],"bpm":125,"playerSec":true,"startTime":282240,"changeBPM":false,"endTime":284160},{"lengthInSteps":16,"sectionNotes":[],"bpm":125,"playerSec":true,"startTime":284160,"changeBPM":false,"endTime":286080},{"lengthInSteps":16,"sectionNotes":[],"bpm":125,"playerSec":true,"startTime":286080,"changeBPM":false,"endTime":288000},{"lengthInSteps":16,"sectionNotes":[],"bpm":125,"playerSec":true,"startTime":288000,"changeBPM":false,"endTime":289920},{"lengthInSteps":16,"sectionNotes":[],"bpm":125,"playerSec":true,"startTime":289920,"changeBPM":false,"endTime":291840},{"lengthInSteps":16,"sectionNotes":[],"bpm":125,"playerSec":true,"startTime":291840,"changeBPM":false,"endTime":293760},{"lengthInSteps":16,"sectionNotes":[],"bpm":125,"playerSec":true,"startTime":293760,"changeBPM":false,"endTime":295680},{"lengthInSteps":16,"sectionNotes":[],"bpm":125,"playerSec":true,"startTime":295680,"changeBPM":false,"endTime":297600},{"lengthInSteps":16,"sectionNotes":[],"bpm":125,"playerSec":true,"startTime":297600,"changeBPM":false,"endTime":299520},{"lengthInSteps":16,"sectionNotes":[],"bpm":125,"playerSec":true,"startTime":299520,"changeBPM":false,"endTime":301440},{"lengthInSteps":16,"sectionNotes":[],"bpm":125,"playerSec":true,"startTime":301440,"changeBPM":false,"endTime":303360},{"lengthInSteps":16,"sectionNotes":[],"bpm":125,"playerSec":true,"startTime":303360,"changeBPM":false,"endTime":305280},{"lengthInSteps":16,"sectionNotes":[],"bpm":125,"playerSec":true,"startTime":305280,"changeBPM":false,"endTime":307200},{"lengthInSteps":16,"sectionNotes":[],"bpm":125,"playerSec":true,"startTime":307200,"changeBPM":false,"endTime":309120},{"lengthInSteps":16,"sectionNotes":[],"bpm":125,"playerSec":true,"startTime":309120,"changeBPM":false,"endTime":311040},{"lengthInSteps":16,"sectionNotes":[],"bpm":125,"playerSec":true,"startTime":311040,"changeBPM":false,"endTime":312960},{"lengthInSteps":16,"sectionNotes":[],"bpm":125,"playerSec":true,"startTime":312960,"changeBPM":false,"endTime":314880},{"lengthInSteps":16,"sectionNotes":[],"bpm":125,"playerSec":true,"startTime":314880,"changeBPM":false,"endTime":316800},{"lengthInSteps":16,"sectionNotes":[],"bpm":125,"playerSec":true,"startTime":316800,"changeBPM":false,"endTime":318720},{"lengthInSteps":16,"sectionNotes":[],"bpm":125,"playerSec":true,"startTime":318720,"changeBPM":false,"endTime":320640},{"lengthInSteps":16,"sectionNotes":[],"bpm":125,"playerSec":true,"startTime":320640,"changeBPM":false,"endTime":322560},{"lengthInSteps":16,"sectionNotes":[],"bpm":125,"playerSec":true,"startTime":322560,"changeBPM":false,"endTime":324480},{"lengthInSteps":16,"sectionNotes":[],"bpm":125,"playerSec":true,"startTime":324480,"changeBPM":false,"endTime":326400},{"lengthInSteps":16,"sectionNotes":[],"bpm":125,"playerSec":true,"startTime":326400,"changeBPM":false,"endTime":328320},{"lengthInSteps":16,"sectionNotes":[],"bpm":125,"playerSec":true,"startTime":328320,"changeBPM":false,"endTime":330240},{"lengthInSteps":16,"sectionNotes":[],"bpm":125,"playerSec":true,"startTime":330240,"changeBPM":false,"endTime":332160},{"lengthInSteps":16,"sectionNotes":[],"bpm":125,"playerSec":true,"startTime":332160,"changeBPM":false,"endTime":334080},{"lengthInSteps":16,"sectionNotes":[],"bpm":125,"playerSec":true,"startTime":334080,"changeBPM":false,"endTime":336000},{"lengthInSteps":16,"sectionNotes":[],"bpm":125,"playerSec":true,"startTime":336000,"changeBPM":false,"endTime":337920}],"player2":"mom-car","audioFile":"high","offset":0,"song":"High","validScore":true,"speed":1.8,"gfVersion":"gf-car","chartVersion":"KEC1","eventObjects":[{"name":"Init BPM","position":0,"value":125,"value2":"1","type":"BPM Change"}],"needsVoices":true,"stage":"limo","noteStyle":"normal","bpm":125}}