{"song":{"player1":"bf","songId":"south","songName":"South","splitVoiceTracks":true,"style":"Default","notes":[{"sectionNotes":[],"lengthInSteps":16,"endTime":1454.54545454545,"mustHitSection":true,"startTime":0},{"sectionNotes":[],"lengthInSteps":16,"endTime":2909.09090909091,"mustHitSection":true,"startTime":1454.54545454545},{"sectionNotes":[],"lengthInSteps":16,"endTime":4363.63636363636,"mustHitSection":true,"startTime":2909.09090909091},{"sectionNotes":[],"lengthInSteps":16,"endTime":5818.18181818182,"mustHitSection":true,"startTime":4363.63636363636},{"sectionNotes":[],"lengthInSteps":16,"endTime":7272.72727272727,"mustHitSection":true,"startTime":5818.18181818182},{"sectionNotes":[],"lengthInSteps":16,"endTime":8727.27272727273,"mustHitSection":true,"startTime":7272.72727272727},{"sectionNotes":[],"lengthInSteps":16,"endTime":10181.8181818182,"mustHitSection":true,"startTime":8727.27272727273},{"sectionNotes":[],"lengthInSteps":16,"endTime":11636.3636363636,"mustHitSection":true,"startTime":10181.8181818182},{"playerSec":false,"sectionNotes":[[11636.3633,3,0,"Normal"],[12000,3,0,"Normal"],[12363.6367,0,0,"Normal"],[12545.4541,3,0,"Normal"],[12727.2725,2,0,"Normal"],[12909.0908,3,0,"Normal"]],"lengthInSteps":16,"endTime":13090.9090909091,"mustHitSection":false,"startTime":11636.3636363636},{"playerSec":false,"sectionNotes":[[13090.9092,0,0,"Normal"],[13454.5449,1,0,"Normal"],[13818.1816,3,0,"Normal"],[14000,3,0,"Normal"],[14181.8184,3,181.818176,"Normal"]],"lengthInSteps":16,"endTime":14545.4545454545,"mustHitSection":false,"startTime":13090.9090909091},{"playerSec":false,"sectionNotes":[[14545.4541,3,0,"Normal"],[14909.0908,3,0,"Normal"],[15272.7275,3,0,"Normal"],[15454.5449,2,0,"Normal"],[15636.3633,0,0,"Normal"],[15818.1816,1,0,"Normal"]],"lengthInSteps":16,"endTime":16000,"mustHitSection":false,"startTime":14545.4545454545},{"playerSec":false,"sectionNotes":[[16000,0,0,"Normal"],[16363.6357,0,0,"Normal"],[16727.2734,2,0,"Normal"],[17090.9082,0,0,"Normal"],[17272.7266,3,0,"Normal"]],"lengthInSteps":16,"endTime":17454.5454545455,"mustHitSection":false,"startTime":16000},{"playerSec":true,"sectionNotes":[[17454.5449,7,0,"Normal"],[17818.1816,7,0,"Normal"],[18181.8184,4,0,"Normal"],[18363.6367,7,0,"Normal"],[18545.4551,6,0,"Normal"],[18727.2734,7,0,"Normal"]],"lengthInSteps":16,"endTime":18909.0909090909,"mustHitSection":true,"startTime":17454.5454545455},{"playerSec":true,"sectionNotes":[[18909.09,4,0,"Normal"],[19272.7266,5,0,"Normal"],[19636.3633,7,0,"Normal"],[19818.1816,7,0,"Normal"],[20000,7,181.818176,"Normal"]],"lengthInSteps":16,"endTime":20363.6363636364,"mustHitSection":true,"startTime":18909.0909090909},{"playerSec":true,"sectionNotes":[[20363.6367,7,0,"Normal"],[20727.2734,7,0,"Normal"],[21090.9082,7,0,"Normal"],[21272.7266,6,0,"Normal"],[21454.5449,4,0,"Normal"],[21636.3633,5,0,"Normal"]],"lengthInSteps":16,"endTime":21818.1818181818,"mustHitSection":true,"startTime":20363.6363636364},{"playerSec":true,"sectionNotes":[[21818.1816,4,0,"Normal"],[22181.8184,4,0,"Normal"],[22545.4551,6,0,"Normal"],[22909.09,4,0,"Normal"],[23090.9082,7,0,"Normal"]],"lengthInSteps":16,"endTime":23272.7272727273,"mustHitSection":true,"startTime":21818.1818181818},{"playerSec":false,"sectionNotes":[[23272.7266,2,0,"Normal"],[23454.5449,1,0,"Normal"],[23636.3633,0,0,"Normal"],[23818.1816,0,0,"Normal"],[23909.09,3,0,"Normal"],[24000,2,0,"Normal"],[24181.8184,0,0,"Normal"],[24363.6367,2,0,"Normal"],[24545.4551,1,0,"Normal"]],"lengthInSteps":16,"endTime":24727.2727272727,"mustHitSection":false,"startTime":23272.7272727273},{"playerSec":false,"sectionNotes":[[24727.2734,2,0,"Normal"],[25090.9082,2,0,"Normal"],[25454.5449,2,0,"Normal"],[25636.3633,1,0,"Normal"],[25818.1816,0,0,"Normal"],[26000,3,0,"Normal"]],"lengthInSteps":16,"endTime":26181.8181818182,"mustHitSection":false,"startTime":24727.2727272727},{"playerSec":false,"sectionNotes":[[26181.8184,0,0,"Normal"],[26545.4551,0,0,"Normal"],[26727.2734,0,0,"Normal"],[26818.1816,2,0,"Normal"],[26909.09,3,0,"Normal"],[27090.9082,0,0,"Normal"],[27272.7266,1,0,"Normal"],[27454.5449,3,0,"Normal"]],"lengthInSteps":16,"endTime":27636.3636363636,"mustHitSection":false,"startTime":26181.8181818182},{"playerSec":false,"sectionNotes":[[27636.3633,2,0,"Normal"],[28000,2,0,"Normal"],[28363.6367,2,0,"Normal"],[28545.4551,3,0,"Normal"],[28727.2715,0,0,"Normal"],[28909.09,1,0,"Normal"]],"lengthInSteps":16,"endTime":29090.9090909091,"mustHitSection":false,"startTime":27636.3636363636},{"playerSec":true,"sectionNotes":[[29090.9082,6,0,"Normal"],[29272.7266,5,0,"Normal"],[29454.5449,4,0,"Normal"],[29636.3633,4,0,"Normal"],[29727.2715,7,0,"Normal"],[29818.1816,6,0,"Normal"],[30000,4,0,"Normal"],[30181.8184,6,0,"Normal"],[30363.6367,5,0,"Normal"]],"lengthInSteps":16,"endTime":30545.4545454545,"mustHitSection":true,"startTime":29090.9090909091},{"playerSec":true,"sectionNotes":[[30545.4551,6,0,"Normal"],[30909.09,6,0,"Normal"],[31272.7266,6,0,"Normal"],[31454.5449,5,0,"Normal"],[31636.3633,4,0,"Normal"],[31818.1816,7,0,"Normal"]],"lengthInSteps":16,"endTime":32000,"mustHitSection":true,"startTime":30545.4545454545},{"playerSec":true,"sectionNotes":[[32000,4,0,"Normal"],[32363.6367,4,0,"Normal"],[32545.4551,4,0,"Normal"],[32636.3633,6,0,"Normal"],[32727.2715,7,0,"Normal"],[32909.09,4,0,"Normal"],[33090.91,5,0,"Normal"],[33272.7266,7,0,"Normal"]],"lengthInSteps":16,"endTime":33454.5454545455,"mustHitSection":true,"startTime":32000},{"playerSec":true,"sectionNotes":[[33454.5469,6,0,"Normal"],[33818.18,6,0,"Normal"],[34181.8164,6,0,"Normal"],[34363.6367,7,0,"Normal"],[34545.4531,4,0,"Normal"],[34727.2734,5,0,"Normal"]],"lengthInSteps":16,"endTime":34909.0909090909,"mustHitSection":true,"startTime":33454.5454545455},{"playerSec":false,"sectionNotes":[[34909.09,2,0,"Normal"],[35090.91,3,0,"Normal"],[35272.7266,0,0,"Normal"],[35454.5469,2,0,"Normal"],[35636.3633,3,0,"Normal"],[35818.18,0,0,"Normal"],[36000,2,0,"Normal"],[36181.8164,3,0,"Normal"]],"lengthInSteps":16,"endTime":36363.6363636364,"mustHitSection":false,"startTime":34909.0909090909},{"playerSec":false,"sectionNotes":[[36363.6367,0,0,"Normal"],[36545.4531,2,0,"Normal"],[36727.2734,3,0,"Normal"],[36909.09,0,0,"Normal"],[37090.91,0,0,"Normal"],[37272.7266,3,0,"Normal"],[37454.5469,0,0,"Normal"]],"lengthInSteps":16,"endTime":37818.1818181818,"mustHitSection":false,"startTime":36363.6363636364},{"playerSec":false,"sectionNotes":[[37818.18,2,0,"Normal"],[38000,3,0,"Normal"],[38181.8164,0,0,"Normal"],[38363.6367,2,0,"Normal"],[38545.4531,3,0,"Normal"],[38727.2734,0,0,"Normal"],[38909.09,2,0,"Normal"],[39090.91,3,0,"Normal"]],"lengthInSteps":16,"endTime":39272.7272727273,"mustHitSection":false,"startTime":37818.1818181818},{"playerSec":false,"sectionNotes":[[39272.7266,0,0,"Normal"],[39454.5469,1,0,"Normal"],[39636.3633,3,0,"Normal"],[39818.18,0,0,"Normal"],[40000,3,0,"Normal"],[40181.8164,0,0,"Normal"],[40363.6367,3,0,"Normal"]],"lengthInSteps":16,"endTime":40727.2727272727,"mustHitSection":false,"startTime":39272.7272727273},{"playerSec":true,"sectionNotes":[[40727.2734,6,0,"Normal"],[40909.09,7,0,"Normal"],[41090.91,4,0,"Normal"],[41272.7266,6,0,"Normal"],[41454.5469,7,0,"Normal"],[41636.3633,4,0,"Normal"],[41818.18,6,0,"Normal"],[42000,7,0,"Normal"]],"lengthInSteps":16,"endTime":42181.8181818182,"mustHitSection":true,"startTime":40727.2727272727},{"playerSec":true,"sectionNotes":[[42181.8164,4,0,"Normal"],[42363.6367,6,0,"Normal"],[42545.4531,7,0,"Normal"],[42727.2734,4,0,"Normal"],[42909.09,4,0,"Normal"],[43090.91,7,0,"Normal"],[43272.7266,4,0,"Normal"]],"lengthInSteps":16,"endTime":43636.3636363636,"mustHitSection":true,"startTime":42181.8181818182},{"playerSec":true,"sectionNotes":[[43636.3633,6,0,"Normal"],[43818.18,7,0,"Normal"],[44000,4,0,"Normal"],[44181.8164,6,0,"Normal"],[44363.6367,7,0,"Normal"],[44545.4531,4,0,"Normal"],[44727.2734,6,0,"Normal"],[44909.09,7,0,"Normal"]],"lengthInSteps":16,"endTime":45090.9090909091,"mustHitSection":true,"startTime":43636.3636363636},{"playerSec":true,"sectionNotes":[[45090.91,4,0,"Normal"],[45272.7266,5,0,"Normal"],[45454.5469,7,0,"Normal"],[45636.3633,4,0,"Normal"],[45818.18,7,0,"Normal"],[46000,4,0,"Normal"],[46181.8164,7,0,"Normal"]],"lengthInSteps":16,"endTime":46545.4545454545,"mustHitSection":true,"startTime":45090.9090909091},{"playerSec":false,"sectionNotes":[[46545.4531,0,0,"Normal"],[46818.18,3,0,"Normal"],[46909.09,1,0,"Normal"],[47090.91,0,0,"Normal"],[47272.7266,3,0,"Normal"],[47454.5469,1,0,"Normal"],[47636.3633,2,0,"Normal"],[47818.18,3,0,"Normal"]],"lengthInSteps":16,"endTime":48000,"mustHitSection":false,"startTime":46545.4545454545},{"playerSec":false,"sectionNotes":[[48000,0,0,"Normal"],[48181.8164,2,0,"Normal"],[48363.6367,3,0,"Normal"],[48545.4531,0,0,"Normal"],[48727.2734,3,0,"Normal"],[48909.09,2,0,"Normal"],[49090.91,0,0,"Normal"]],"lengthInSteps":16,"endTime":49454.5454545455,"mustHitSection":false,"startTime":48000},{"playerSec":false,"sectionNotes":[[49454.5469,0,0,"Normal"],[49545.4531,3,0,"Normal"],[49636.3633,2,0,"Normal"],[49818.18,3,0,"Normal"],[50000,0,0,"Normal"],[50181.8164,2,0,"Normal"],[50363.6367,3,0,"Normal"],[50545.4531,0,0,"Normal"],[50636.3633,3,0,"Normal"],[50727.2734,2,0,"Normal"]],"lengthInSteps":16,"endTime":50909.0909090909,"mustHitSection":false,"startTime":49454.5454545455},{"playerSec":false,"sectionNotes":[[50909.09,1,0,"Normal"],[51090.91,1,0,"Normal"],[51272.7266,0,0,"Normal"],[51454.5469,3,0,"Normal"],[51636.3633,2,0,"Normal"],[51818.18,3,0,"Normal"],[52000,0,0,"Normal"]],"lengthInSteps":16,"endTime":52363.6363636364,"mustHitSection":false,"startTime":50909.0909090909},{"playerSec":true,"sectionNotes":[[52363.6367,4,0,"Normal"],[52636.3633,7,0,"Normal"],[52727.2734,5,0,"Normal"],[52909.09,4,0,"Normal"],[53090.91,7,0,"Normal"],[53272.7266,5,0,"Normal"],[53454.5469,6,0,"Normal"],[53636.3633,7,0,"Normal"]],"lengthInSteps":16,"endTime":53818.1818181818,"mustHitSection":true,"startTime":52363.6363636364},{"playerSec":true,"sectionNotes":[[53818.18,4,0,"Normal"],[54000,6,0,"Normal"],[54181.8164,7,0,"Normal"],[54363.6367,4,0,"Normal"],[54545.4531,7,0,"Normal"],[54727.2734,6,0,"Normal"],[54909.09,4,0,"Normal"]],"lengthInSteps":16,"endTime":55272.7272727273,"mustHitSection":true,"startTime":53818.1818181818},{"playerSec":true,"sectionNotes":[[55272.7266,4,0,"Normal"],[55363.6367,7,0,"Normal"],[55454.5469,6,0,"Normal"],[55636.3633,7,0,"Normal"],[55818.18,4,0,"Normal"],[56000,6,0,"Normal"],[56181.8164,7,0,"Normal"],[56363.6367,4,0,"Normal"],[56454.543,7,0,"Normal"],[56545.4531,6,0,"Normal"]],"lengthInSteps":16,"endTime":56727.2727272727,"mustHitSection":true,"startTime":55272.7272727273},{"playerSec":true,"sectionNotes":[[56727.2734,5,0,"Normal"],[56909.09,5,0,"Normal"],[57090.91,4,0,"Normal"],[57272.7266,7,0,"Normal"],[57454.543,0,0,"Normal"],[57454.543,6,0,"Normal"],[57636.3633,3,0,"Normal"],[57636.3633,7,0,"Normal"],[57818.18,1,0,"Normal"],[57818.18,4,0,"Normal"],[58000,3,0,"Normal"]],"lengthInSteps":16,"endTime":58181.8181818182,"mustHitSection":true,"startTime":56727.2727272727},{"playerSec":false,"sectionNotes":[[58181.8164,3,0,"Normal"],[58545.4531,3,0,"Normal"],[58727.2734,1,0,"Normal"],[58909.09,2,0,"Normal"],[59090.91,0,0,"Normal"],[59272.7266,1,0,"Normal"],[59454.543,3,0,"Normal"]],"lengthInSteps":16,"endTime":59636.3636363636,"mustHitSection":false,"startTime":58181.8181818182},{"playerSec":false,"sectionNotes":[[59636.3633,0,272.727264,"Normal"],[60000,2,0,"Normal"],[60363.6367,2,0,"Normal"],[60545.4531,2,0,"Normal"],[60727.2734,2,181.818176,"Normal"]],"lengthInSteps":16,"endTime":61090.9090909091,"mustHitSection":false,"startTime":59636.3636363636},{"playerSec":false,"sectionNotes":[[61090.91,2,0,"Normal"],[61454.543,2,0,"Normal"],[61636.3633,3,0,"Normal"],[61818.18,1,0,"Normal"],[62000,0,0,"Normal"],[62181.8164,3,0,"Normal"],[62363.6367,0,0,"Normal"]],"lengthInSteps":16,"endTime":62545.4545454545,"mustHitSection":false,"startTime":61090.9090909091},{"playerSec":false,"sectionNotes":[[62545.4531,0,0,"Normal"],[62909.09,0,0,"Normal"],[63272.7266,4,0,"Normal"],[63272.7266,2,0,"Normal"],[63454.543,7,0,"Normal"],[63636.3633,5,0,"Normal"],[63636.3633,0,0,"Normal"],[63818.18,7,0,"Normal"],[63818.18,3,0,"Normal"]],"lengthInSteps":16,"endTime":64000,"mustHitSection":false,"startTime":62545.4545454545},{"playerSec":true,"sectionNotes":[[64000,7,0,"Normal"],[64363.6367,7,0,"Normal"],[64545.4531,5,0,"Normal"],[64727.2734,6,0,"Normal"],[64909.09,4,0,"Normal"],[65090.91,5,0,"Normal"],[65272.7266,7,0,"Normal"]],"lengthInSteps":16,"endTime":65454.5454545455,"mustHitSection":true,"startTime":64000},{"playerSec":true,"sectionNotes":[[65454.543,4,272.727264,"Normal"],[65818.18,6,0,"Normal"],[66181.82,6,0,"Normal"],[66363.63,6,0,"Normal"],[66545.45,6,181.818176,"Normal"]],"lengthInSteps":16,"endTime":66909.0909090909,"mustHitSection":true,"startTime":65454.5454545455},{"playerSec":true,"sectionNotes":[[66909.09,6,0,"Normal"],[67272.73,6,0,"Normal"],[67454.55,7,0,"Normal"],[67636.36,5,0,"Normal"],[67818.18,4,0,"Normal"],[68000,7,0,"Normal"],[68181.82,4,0,"Normal"]],"lengthInSteps":16,"endTime":68363.6363636364,"mustHitSection":true,"startTime":66909.0909090909},{"playerSec":true,"sectionNotes":[[68363.63,4,0,"Normal"],[68727.27,4,0,"Normal"],[69090.91,6,0,"Normal"],[69454.55,4,0,"Normal"],[69636.36,7,0,"Normal"]],"lengthInSteps":16,"endTime":69818.1818181818,"mustHitSection":true,"startTime":68363.6363636364},{"playerSec":false,"sectionNotes":[[69818.18,2,0,"Normal"],[70000,3,0,"Normal"],[70181.82,0,0,"Normal"],[70363.63,3,0,"Normal"],[70454.55,2,0,"Normal"],[70545.45,0,0,"Normal"],[70727.27,3,0,"Normal"],[70909.09,2,0,"Normal"],[71090.91,3,0,"Normal"]],"lengthInSteps":16,"endTime":71272.7272727273,"mustHitSection":false,"startTime":69818.1818181818},{"playerSec":false,"sectionNotes":[[71272.73,2,0,"Normal"],[71636.36,2,0,"Normal"],[71818.18,0,0,"Normal"],[72000,2,0,"Normal"],[72181.82,3,0,"Normal"],[72363.63,0,0,"Normal"],[72545.45,2,0,"Normal"]],"lengthInSteps":16,"endTime":72727.2727272727,"mustHitSection":false,"startTime":71272.7272727273},{"playerSec":false,"sectionNotes":[[72727.27,0,0,"Normal"],[73090.91,0,0,"Normal"],[73272.73,0,0,"Normal"],[73363.63,3,0,"Normal"],[73454.55,2,0,"Normal"],[73636.36,3,0,"Normal"],[73818.18,2,0,"Normal"],[74000,0,0,"Normal"]],"lengthInSteps":16,"endTime":74181.8181818182,"mustHitSection":false,"startTime":72727.2727272727},{"playerSec":false,"sectionNotes":[[74181.82,2,0,"Normal"],[74363.63,3,0,"Normal"],[74545.45,2,0,"Normal"],[74727.27,0,0,"Normal"],[74909.09,1,0,"Normal"],[75090.91,3,0,"Normal"],[75272.73,0,0,"Normal"],[75454.55,3,0,"Normal"]],"lengthInSteps":16,"endTime":75636.3636363636,"mustHitSection":false,"startTime":74181.8181818182},{"playerSec":true,"sectionNotes":[[75636.36,6,0,"Normal"],[75818.18,7,0,"Normal"],[76000,4,0,"Normal"],[76181.82,7,0,"Normal"],[76272.73,6,0,"Normal"],[76363.63,4,0,"Normal"],[76545.45,7,0,"Normal"],[76727.27,6,0,"Normal"],[76909.09,7,0,"Normal"]],"lengthInSteps":16,"endTime":77090.9090909091,"mustHitSection":true,"startTime":75636.3636363636},{"playerSec":true,"sectionNotes":[[77090.91,6,0,"Normal"],[77454.55,6,0,"Normal"],[77636.36,4,0,"Normal"],[77818.18,6,0,"Normal"],[78000,7,0,"Normal"],[78181.82,4,0,"Normal"],[78363.63,6,0,"Normal"]],"lengthInSteps":16,"endTime":78545.4545454545,"mustHitSection":true,"startTime":77090.9090909091},{"playerSec":true,"sectionNotes":[[78545.45,4,0,"Normal"],[78909.09,4,0,"Normal"],[79090.91,4,0,"Normal"],[79181.82,7,0,"Normal"],[79272.73,6,0,"Normal"],[79454.55,7,0,"Normal"],[79636.36,6,0,"Normal"],[79818.18,4,0,"Normal"]],"lengthInSteps":16,"endTime":80000,"mustHitSection":true,"startTime":78545.4545454545},{"playerSec":true,"sectionNotes":[[80000,6,0,"Normal"],[80181.82,7,0,"Normal"],[80363.63,6,0,"Normal"],[80545.45,4,0,"Normal"],[80727.27,5,0,"Normal"],[80909.09,7,0,"Normal"],[81090.91,4,0,"Normal"],[81272.73,7,0,"Normal"]],"lengthInSteps":16,"endTime":81454.5454545455,"mustHitSection":true,"startTime":80000},{"sectionNotes":[],"lengthInSteps":16,"endTime":82909.0909090909,"mustHitSection":true,"startTime":81454.5454545455},{"sectionNotes":[],"lengthInSteps":16,"endTime":84363.6363636364,"mustHitSection":true,"startTime":82909.0909090909},{"sectionNotes":[],"lengthInSteps":16,"endTime":85818.1818181818,"mustHitSection":true,"startTime":84363.6363636364},{"sectionNotes":[],"lengthInSteps":16,"endTime":87272.7272727273,"mustHitSection":true,"startTime":85818.1818181818},{"sectionNotes":[],"lengthInSteps":16,"endTime":88727.2727272727,"mustHitSection":true,"startTime":87272.7272727273},{"endTime":90181.8181818182,"altAnim":false,"mustHitSection":true,"lengthInSteps":16,"typeOfSection":0,"sectionNotes":[],"changeBPM":false,"startTime":88727.2727272727,"bpm":165},{"endTime":91636.3636363636,"playerAltAnim":false,"altAnim":false,"CPUAltAnim":false,"mustHitSection":true,"lengthInSteps":16,"typeOfSection":0,"sectionNotes":[],"bpm":165,"startTime":90181.8181818182,"changeBPM":false},{"endTime":93090.9090909091,"playerAltAnim":false,"altAnim":false,"CPUAltAnim":false,"mustHitSection":true,"lengthInSteps":16,"typeOfSection":0,"sectionNotes":[],"bpm":165,"startTime":91636.3636363636,"changeBPM":false},{"endTime":94545.4545454545,"playerAltAnim":false,"altAnim":false,"CPUAltAnim":false,"mustHitSection":true,"lengthInSteps":16,"typeOfSection":0,"sectionNotes":[],"bpm":165,"startTime":93090.9090909091,"changeBPM":false},{"endTime":96000,"playerAltAnim":false,"altAnim":false,"CPUAltAnim":false,"mustHitSection":true,"lengthInSteps":16,"typeOfSection":0,"sectionNotes":[],"bpm":165,"startTime":94545.4545454545,"changeBPM":false},{"endTime":97454.5454545455,"playerAltAnim":false,"altAnim":false,"CPUAltAnim":false,"mustHitSection":true,"lengthInSteps":16,"typeOfSection":0,"sectionNotes":[],"bpm":165,"startTime":96000,"changeBPM":false},{"endTime":98909.0909090909,"playerAltAnim":false,"altAnim":false,"CPUAltAnim":false,"mustHitSection":true,"lengthInSteps":16,"typeOfSection":0,"sectionNotes":[],"bpm":165,"startTime":97454.5454545455,"changeBPM":false},{"endTime":100363.636363636,"playerAltAnim":false,"altAnim":false,"CPUAltAnim":false,"mustHitSection":true,"lengthInSteps":16,"typeOfSection":0,"sectionNotes":[],"bpm":165,"startTime":98909.0909090909,"changeBPM":false},{"endTime":101818.181818182,"playerAltAnim":false,"altAnim":false,"CPUAltAnim":false,"mustHitSection":true,"lengthInSteps":16,"typeOfSection":0,"sectionNotes":[],"bpm":165,"startTime":100363.636363636,"changeBPM":false},{"endTime":103272.727272727,"playerAltAnim":false,"altAnim":false,"CPUAltAnim":false,"mustHitSection":true,"lengthInSteps":16,"typeOfSection":0,"sectionNotes":[],"bpm":165,"startTime":101818.181818182,"changeBPM":false},{"endTime":104727.272727273,"playerAltAnim":false,"altAnim":false,"CPUAltAnim":false,"mustHitSection":true,"lengthInSteps":16,"typeOfSection":0,"sectionNotes":[],"bpm":165,"startTime":103272.727272727,"changeBPM":false},{"endTime":106181.818181818,"playerAltAnim":false,"altAnim":false,"CPUAltAnim":false,"mustHitSection":true,"lengthInSteps":16,"typeOfSection":0,"sectionNotes":[],"bpm":165,"startTime":104727.272727273,"changeBPM":false},{"endTime":107636.363636364,"playerAltAnim":false,"altAnim":false,"CPUAltAnim":false,"mustHitSection":true,"lengthInSteps":16,"typeOfSection":0,"sectionNotes":[],"bpm":165,"startTime":106181.818181818,"changeBPM":false},{"endTime":109090.909090909,"playerAltAnim":false,"altAnim":false,"CPUAltAnim":false,"mustHitSection":true,"lengthInSteps":16,"typeOfSection":0,"sectionNotes":[],"bpm":165,"startTime":107636.363636364,"changeBPM":false},{"endTime":110545.454545455,"playerAltAnim":false,"altAnim":false,"CPUAltAnim":false,"mustHitSection":true,"lengthInSteps":16,"typeOfSection":0,"sectionNotes":[],"bpm":165,"startTime":109090.909090909,"changeBPM":false},{"endTime":112000,"playerAltAnim":false,"altAnim":false,"CPUAltAnim":false,"mustHitSection":true,"lengthInSteps":16,"typeOfSection":0,"sectionNotes":[],"bpm":165,"startTime":110545.454545455,"changeBPM":false},{"endTime":113454.545454545,"playerAltAnim":false,"altAnim":false,"CPUAltAnim":false,"mustHitSection":true,"lengthInSteps":16,"typeOfSection":0,"sectionNotes":[],"bpm":165,"startTime":112000,"changeBPM":false},{"endTime":114909.090909091,"playerAltAnim":false,"altAnim":false,"CPUAltAnim":false,"mustHitSection":true,"lengthInSteps":16,"typeOfSection":0,"sectionNotes":[],"bpm":165,"startTime":113454.545454545,"changeBPM":false},{"endTime":116363.636363636,"playerAltAnim":false,"altAnim":false,"CPUAltAnim":false,"mustHitSection":true,"lengthInSteps":16,"typeOfSection":0,"sectionNotes":[],"bpm":165,"startTime":114909.090909091,"changeBPM":false},{"endTime":117818.181818182,"playerAltAnim":false,"altAnim":false,"CPUAltAnim":false,"mustHitSection":true,"lengthInSteps":16,"typeOfSection":0,"sectionNotes":[],"bpm":165,"startTime":116363.636363636,"changeBPM":false},{"endTime":119272.727272727,"playerAltAnim":false,"altAnim":false,"CPUAltAnim":false,"mustHitSection":true,"lengthInSteps":16,"typeOfSection":0,"sectionNotes":[],"bpm":165,"startTime":117818.181818182,"changeBPM":false},{"endTime":120727.272727273,"playerAltAnim":false,"altAnim":false,"CPUAltAnim":false,"mustHitSection":true,"lengthInSteps":16,"typeOfSection":0,"sectionNotes":[],"bpm":165,"startTime":119272.727272727,"changeBPM":false},{"endTime":122181.818181818,"playerAltAnim":false,"altAnim":false,"CPUAltAnim":false,"mustHitSection":true,"lengthInSteps":16,"typeOfSection":0,"sectionNotes":[],"bpm":165,"startTime":120727.272727273,"changeBPM":false},{"endTime":123636.363636364,"playerAltAnim":false,"altAnim":false,"CPUAltAnim":false,"mustHitSection":true,"lengthInSteps":16,"typeOfSection":0,"sectionNotes":[],"bpm":165,"startTime":122181.818181818,"changeBPM":false},{"endTime":125090.909090909,"playerAltAnim":false,"altAnim":false,"CPUAltAnim":false,"mustHitSection":true,"lengthInSteps":16,"typeOfSection":0,"sectionNotes":[],"bpm":165,"startTime":123636.363636364,"changeBPM":false},{"endTime":126545.454545455,"playerAltAnim":false,"altAnim":false,"CPUAltAnim":false,"mustHitSection":true,"lengthInSteps":16,"typeOfSection":0,"sectionNotes":[],"bpm":165,"startTime":125090.909090909,"changeBPM":false},{"endTime":128000,"playerAltAnim":false,"altAnim":false,"CPUAltAnim":false,"mustHitSection":true,"lengthInSteps":16,"typeOfSection":0,"sectionNotes":[],"bpm":165,"startTime":126545.454545455,"changeBPM":false},{"endTime":129454.545454545,"playerAltAnim":false,"altAnim":false,"CPUAltAnim":false,"mustHitSection":true,"lengthInSteps":16,"typeOfSection":0,"sectionNotes":[],"bpm":165,"startTime":128000,"changeBPM":false},{"endTime":130909.090909091,"playerAltAnim":false,"altAnim":false,"CPUAltAnim":false,"mustHitSection":true,"lengthInSteps":16,"typeOfSection":0,"sectionNotes":[],"bpm":165,"startTime":129454.545454545,"changeBPM":false},{"endTime":132363.636363636,"playerAltAnim":false,"altAnim":false,"CPUAltAnim":false,"mustHitSection":true,"lengthInSteps":16,"typeOfSection":0,"sectionNotes":[],"bpm":165,"startTime":130909.090909091,"changeBPM":false},{"endTime":133818.181818182,"playerAltAnim":false,"altAnim":false,"CPUAltAnim":false,"mustHitSection":true,"lengthInSteps":16,"typeOfSection":0,"sectionNotes":[],"bpm":165,"startTime":132363.636363636,"changeBPM":false},{"endTime":135272.727272727,"playerAltAnim":false,"altAnim":false,"CPUAltAnim":false,"mustHitSection":true,"lengthInSteps":16,"typeOfSection":0,"sectionNotes":[],"bpm":165,"startTime":133818.181818182,"changeBPM":false},{"endTime":136727.272727273,"playerAltAnim":false,"altAnim":false,"CPUAltAnim":false,"mustHitSection":true,"lengthInSteps":16,"typeOfSection":0,"sectionNotes":[],"bpm":165,"startTime":135272.727272727,"changeBPM":false},{"endTime":138181.818181818,"playerAltAnim":false,"altAnim":false,"CPUAltAnim":false,"mustHitSection":true,"lengthInSteps":16,"typeOfSection":0,"sectionNotes":[],"bpm":165,"startTime":136727.272727273,"changeBPM":false},{"endTime":139636.363636364,"playerAltAnim":false,"altAnim":false,"CPUAltAnim":false,"mustHitSection":true,"lengthInSteps":16,"typeOfSection":0,"sectionNotes":[],"bpm":165,"startTime":138181.818181818,"changeBPM":false},{"endTime":141090.909090909,"playerAltAnim":false,"altAnim":false,"CPUAltAnim":false,"mustHitSection":true,"lengthInSteps":16,"typeOfSection":0,"sectionNotes":[],"bpm":165,"startTime":139636.363636364,"changeBPM":false},{"endTime":142545.454545455,"playerAltAnim":false,"altAnim":false,"CPUAltAnim":false,"mustHitSection":true,"lengthInSteps":16,"typeOfSection":0,"sectionNotes":[],"bpm":165,"startTime":141090.909090909,"changeBPM":false},{"endTime":144000,"playerAltAnim":false,"altAnim":false,"CPUAltAnim":false,"mustHitSection":true,"lengthInSteps":16,"typeOfSection":0,"sectionNotes":[],"bpm":165,"startTime":142545.454545455,"changeBPM":false},{"endTime":145454.545454545,"playerAltAnim":false,"altAnim":false,"CPUAltAnim":false,"mustHitSection":true,"lengthInSteps":16,"typeOfSection":0,"sectionNotes":[],"bpm":165,"startTime":144000,"changeBPM":false},{"lengthInSteps":16,"sectionNotes":[],"bpm":165,"playerSec":true,"startTime":145454.545454545,"changeBPM":false,"endTime":146909.090909091},{"lengthInSteps":16,"sectionNotes":[],"bpm":165,"playerSec":true,"startTime":146909.090909091,"changeBPM":false,"endTime":148363.636363636},{"lengthInSteps":16,"sectionNotes":[],"bpm":165,"playerSec":true,"startTime":148363.636363636,"changeBPM":false,"endTime":149818.181818182},{"lengthInSteps":16,"sectionNotes":[],"bpm":165,"playerSec":true,"startTime":149818.181818182,"changeBPM":false,"endTime":151272.727272727},{"lengthInSteps":16,"sectionNotes":[],"bpm":165,"playerSec":true,"startTime":151272.727272727,"changeBPM":false,"endTime":152727.272727273},{"lengthInSteps":16,"sectionNotes":[],"bpm":165,"playerSec":true,"startTime":152727.272727273,"changeBPM":false,"endTime":154181.818181818},{"lengthInSteps":16,"sectionNotes":[],"bpm":165,"playerSec":true,"startTime":154181.818181818,"changeBPM":false,"endTime":155636.363636364},{"lengthInSteps":16,"sectionNotes":[],"bpm":165,"playerSec":true,"startTime":155636.363636364,"changeBPM":false,"endTime":157090.909090909},{"lengthInSteps":16,"sectionNotes":[],"bpm":165,"playerSec":true,"startTime":157090.909090909,"changeBPM":false,"endTime":158545.454545455},{"lengthInSteps":16,"sectionNotes":[],"bpm":165,"playerSec":true,"startTime":158545.454545455,"changeBPM":false,"endTime":160000},{"lengthInSteps":16,"sectionNotes":[],"bpm":165,"playerSec":true,"startTime":160000,"changeBPM":false,"endTime":161454.545454545},{"lengthInSteps":16,"sectionNotes":[],"bpm":165,"playerSec":true,"startTime":161454.545454545,"changeBPM":false,"endTime":162909.090909091},{"lengthInSteps":16,"sectionNotes":[],"bpm":165,"playerSec":true,"startTime":162909.090909091,"changeBPM":false,"endTime":164363.636363636},{"lengthInSteps":16,"sectionNotes":[],"bpm":165,"playerSec":true,"startTime":164363.636363636,"changeBPM":false,"endTime":165818.181818182},{"lengthInSteps":16,"sectionNotes":[],"bpm":165,"playerSec":true,"startTime":165818.181818182,"changeBPM":false,"endTime":167272.727272727},{"lengthInSteps":16,"sectionNotes":[],"bpm":165,"playerSec":true,"startTime":167272.727272727,"changeBPM":false,"endTime":168727.272727273},{"lengthInSteps":16,"sectionNotes":[],"bpm":165,"playerSec":true,"startTime":168727.272727273,"changeBPM":false,"endTime":170181.818181818},{"lengthInSteps":16,"sectionNotes":[],"bpm":165,"playerSec":true,"startTime":170181.818181818,"changeBPM":false,"endTime":171636.363636364},{"lengthInSteps":16,"sectionNotes":[],"bpm":165,"playerSec":true,"startTime":171636.363636364,"changeBPM":false,"endTime":173090.909090909},{"lengthInSteps":16,"sectionNotes":[],"bpm":165,"playerSec":true,"startTime":173090.909090909,"changeBPM":false,"endTime":174545.454545455},{"lengthInSteps":16,"sectionNotes":[],"bpm":165,"playerSec":true,"startTime":174545.454545455,"changeBPM":false,"endTime":176000},{"lengthInSteps":16,"sectionNotes":[],"bpm":165,"playerSec":true,"startTime":176000,"changeBPM":false,"endTime":177454.545454545},{"lengthInSteps":16,"sectionNotes":[],"bpm":165,"playerSec":true,"startTime":177454.545454545,"changeBPM":false,"endTime":178909.090909091},{"lengthInSteps":16,"sectionNotes":[],"bpm":165,"playerSec":true,"startTime":178909.090909091,"changeBPM":false,"endTime":180363.636363636},{"lengthInSteps":16,"sectionNotes":[],"bpm":165,"playerSec":true,"startTime":180363.636363636,"changeBPM":false,"endTime":181818.181818182},{"lengthInSteps":16,"sectionNotes":[],"bpm":165,"playerSec":true,"startTime":181818.181818182,"changeBPM":false,"endTime":183272.727272727},{"lengthInSteps":16,"sectionNotes":[],"bpm":165,"playerSec":true,"startTime":183272.727272727,"changeBPM":false,"endTime":184727.272727273},{"lengthInSteps":16,"sectionNotes":[],"bpm":165,"playerSec":true,"startTime":184727.272727273,"changeBPM":false,"endTime":186181.818181818},{"lengthInSteps":16,"sectionNotes":[],"bpm":165,"playerSec":true,"startTime":186181.818181818,"changeBPM":false,"endTime":187636.363636364},{"lengthInSteps":16,"sectionNotes":[],"bpm":165,"playerSec":true,"startTime":187636.363636364,"changeBPM":false,"endTime":189090.909090909},{"lengthInSteps":16,"sectionNotes":[],"bpm":165,"playerSec":true,"startTime":189090.909090909,"changeBPM":false,"endTime":190545.454545455},{"lengthInSteps":16,"sectionNotes":[],"bpm":165,"playerSec":true,"startTime":190545.454545455,"changeBPM":false,"endTime":192000},{"lengthInSteps":16,"sectionNotes":[],"bpm":165,"playerSec":true,"startTime":192000,"changeBPM":false,"endTime":193454.545454545},{"lengthInSteps":16,"sectionNotes":[],"bpm":165,"playerSec":true,"startTime":193454.545454545,"changeBPM":false,"endTime":194909.090909091},{"lengthInSteps":16,"sectionNotes":[],"bpm":165,"playerSec":true,"startTime":194909.090909091,"changeBPM":false,"endTime":196363.636363636},{"lengthInSteps":16,"sectionNotes":[],"bpm":165,"playerSec":true,"startTime":196363.636363636,"changeBPM":false,"endTime":197818.181818182},{"lengthInSteps":16,"sectionNotes":[],"bpm":165,"playerSec":true,"startTime":197818.181818182,"changeBPM":false,"endTime":199272.727272727},{"lengthInSteps":16,"sectionNotes":[],"bpm":165,"playerSec":true,"startTime":199272.727272727,"changeBPM":false,"endTime":200727.272727273},{"lengthInSteps":16,"sectionNotes":[],"bpm":165,"playerSec":true,"startTime":200727.272727273,"changeBPM":false,"endTime":202181.818181818},{"lengthInSteps":16,"sectionNotes":[],"bpm":165,"playerSec":true,"startTime":202181.818181818,"changeBPM":false,"endTime":203636.363636364},{"lengthInSteps":16,"sectionNotes":[],"bpm":165,"playerSec":true,"startTime":203636.363636364,"changeBPM":false,"endTime":205090.909090909},{"lengthInSteps":16,"sectionNotes":[],"bpm":165,"playerSec":true,"startTime":205090.909090909,"changeBPM":false,"endTime":206545.454545455},{"lengthInSteps":16,"sectionNotes":[],"bpm":165,"playerSec":true,"startTime":206545.454545455,"changeBPM":false,"endTime":208000},{"lengthInSteps":16,"sectionNotes":[],"bpm":165,"playerSec":true,"startTime":208000,"changeBPM":false,"endTime":209454.545454545},{"lengthInSteps":16,"sectionNotes":[],"bpm":165,"playerSec":true,"startTime":209454.545454545,"changeBPM":false,"endTime":210909.090909091},{"lengthInSteps":16,"sectionNotes":[],"bpm":165,"playerSec":true,"startTime":210909.090909091,"changeBPM":false,"endTime":212363.636363636},{"lengthInSteps":16,"sectionNotes":[],"bpm":165,"playerSec":true,"startTime":212363.636363636,"changeBPM":false,"endTime":213818.181818182},{"lengthInSteps":16,"sectionNotes":[],"bpm":165,"playerSec":true,"startTime":213818.181818182,"changeBPM":false,"endTime":215272.727272727}],"player2":"spooky","audioFile":"south","offset":0,"song":"South","validScore":true,"speed":1.5,"gfVersion":"gf","chartVersion":"KEC1","eventObjects":[{"name":"Init BPM","position":0,"value":165,"value2":"1","type":"BPM Change"}],"needsVoices":true,"stage":"halloween","noteStyle":"normal","bpm":165}}